[
  {
    "url": "https://budget.canada.ca/2025/report-rapport/toc-tdm-en.html",
    "file": "en/toc-tdm-en.html"
  },
  {
    "url": "https://budget.canada.ca/2025/report-rapport/intro-en.html",
    "file": "en/intro-en.html"
  },
  {
    "url": "https://budget.canada.ca/2025/report-rapport/foreword-avant-propos-en.html",
    "file": "en/foreword-avant-propos-en.html"
  },
  {
    "url": "https://budget.canada.ca/2025/report-rapport/overview-apercu-en.html",
    "file": "en/overview-apercu-en.html"
  },
  {
    "url": "https://budget.canada.ca/2025/report-rapport/chap1-en.html",
    "file": "en/chap1-en.html"
  },
  {
    "url": "https://budget.canada.ca/2025/report-rapport/chap2-en.html",
    "file": "en/chap2-en.html"
  },
  {
    "url": "https://budget.canada.ca/2025/report-rapport/chap3-en.html",
    "file": "en/chap3-en.html"
  },
  {
    "url": "https://budget.canada.ca/2025/report-rapport/chap4-en.html",
    "file": "en/chap4-en.html"
  },
  {
    "url": "https://budget.canada.ca/2025/report-rapport/chap5-en.html",
    "file": "en/chap5-en.html"
  },
  {
    "url": "https://budget.canada.ca/2025/report-rapport/anx1-en.html",
    "file": "en/anx1-en.html"
  },
  {
    "url": "https://budget.canada.ca/2025/report-rapport/anx2-en.html",
    "file": "en/anx2-en.html"
  },
  {
    "url": "https://budget.canada.ca/2025/report-rapport/anx3-en.html",
    "file": "en/anx3-en.html"
  },
  {
    "url": "https://budget.canada.ca/2025/report-rapport/anx4-en.html",
    "file": "en/anx4-en.html"
  },
  {
    "url": "https://budget.canada.ca/2025/report-rapport/anx5-en.html",
    "file": "en/anx5-en.html"
  },
  {
    "url": "https://budget.canada.ca/2025/report-rapport/anx6-en.html",
    "file": "en/anx6-en.html"
  },
  {
    "url": "https://budget.canada.ca/2025/report-rapport/tm-mf-en.html",
    "file": "en/tm-mf-en.html"
  },
  {
    "url": "https://budget.canada.ca/2025/report-rapport/nwmm-amvm-1-en.html",
    "file": "en/nwmm-amvm-1-en.html"
  },
  {
    "url": "https://budget.canada.ca/2025/report-rapport/nwmm-amvm-2-en.html",
    "file": "en/nwmm-amvm-2-en.html"
  },
  {
    "url": "https://budget.canada.ca/2025/report-rapport/nwmm-amvm-3-en.html",
    "file": "en/nwmm-amvm-3-en.html"
  },
  {
    "url": "https://budget.canada.ca/2025/report-rapport/nwmm-amvm-4-en.html",
    "file": "en/nwmm-amvm-4-en.html"
  }
]
